{"trial_id": "0172", "hyperparameters": {"space": [{"class_name": "Int", "config": {"name": "units1", "default": null, "conditions": [], "min_value": 32, "max_value": 320, "step": 16, "sampling": "linear"}}, {"class_name": "Choice", "config": {"name": "activation1", "default": "relu", "conditions": [], "values": ["relu", "tanh", "sigmoid"], "ordered": false}}, {"class_name": "Int", "config": {"name": "units2", "default": null, "conditions": [], "min_value": 16, "max_value": 320, "step": 16, "sampling": "linear"}}, {"class_name": "Choice", "config": {"name": "activation2", "default": "relu", "conditions": [], "values": ["relu", "tanh", "sigmoid"], "ordered": false}}], "values": {"units1": 176, "activation1": "relu", "units2": 272, "activation2": "tanh", "tuner/epochs": 4, "tuner/initial_epoch": 0, "tuner/bracket": 3, "tuner/round": 0}}, "metrics": {"metrics": {"loss": {"direction": "min", "observations": [{"value": [237.43280029296875], "step": 0}]}, "mae": {"direction": "min", "observations": [{"value": [10.10877799987793], "step": 0}]}, "val_loss": {"direction": "min", "observations": [{"value": [163.78749084472656], "step": 0}]}, "val_mae": {"direction": "min", "observations": [{"value": [7.536162376403809], "step": 0}]}}}, "score": 7.536162376403809, "best_step": 0, "status": "COMPLETED", "message": null}